{"Title":"I Am Sam","Year":"2001","Rated":"PG-13","Released":"25 Jan 2002","Runtime":"132 min","Genre":"Drama","Director":"Jessie Nelson","Writer":"Kristine Johnson, Jessie Nelson","Actors":"Sean Penn, Michelle Pfeiffer, Dakota Fanning","Plot":"A mentally handicapped man fights for custody of his 7-year-old daughter and in the process teaches his cold-hearted lawyer the value of love and family.","Language":"English","Country":"United States","Awards":"Nominated for 1 Oscar. 8 wins \u0026 12 nominations total","Poster":"https://m.media-amazon.com/images/M/MV5BYzk5YTdmMzMtMjcyZS00ZDI4LThkMWItZDgwMzI0MzQyNDVjXkEyXkFqcGdeQXVyNjk1Njg5NTA@._V1_SX300.jpg","Ratings":[{"Source":"Internet Movie Database","Value":"7.6/10"},{"Source":"Rotten Tomatoes","Value":"36%"},{"Source":"Metacritic","Value":"28/100"}],"Metascore":"28","imdbRating":"7.6","imdbVotes":"150,251","imdbID":"tt0277027","Type":"movie","DVD":"18 Jan 2005","BoxOffice":"$40,311,852","Response":"True"}